genie/base.py
genie/decorator.cpython-312-aarch64-linux-gnu.so
genie/get_json.cpython-312-aarch64-linux-gnu.so
genie/gre.cpython-312-aarch64-linux-gnu.so
genie/info.cpython-312-aarch64-linux-gnu.so
genie/testbed.cpython-312-aarch64-linux-gnu.so
genie/abstract/__init__.py
genie/abstract/decorator.cpython-312-aarch64-linux-gnu.so
genie/abstract/magic.py
genie/abstract/package.cpython-312-aarch64-linux-gnu.so
genie/abstract/plugin.cpython-312-aarch64-linux-gnu.so
genie/abstract/token.cpython-312-aarch64-linux-gnu.so
genie/abstract/version.cpython-312-aarch64-linux-gnu.so
genie/clean/__init__.py
genie/clean/extend.cpython-312-aarch64-linux-gnu.so
genie/cli/__init__.py
genie/cli/__main__.cpython-312-aarch64-linux-gnu.so
genie/cli/core.cpython-312-aarch64-linux-gnu.so
genie/cli/commands/__init__.py
genie/cli/commands/create.cpython-312-aarch64-linux-gnu.so
genie/cli/commands/create_parser.cpython-312-aarch64-linux-gnu.so
genie/cli/commands/create_testbed.cpython-312-aarch64-linux-gnu.so
genie/cli/commands/create_trigger.cpython-312-aarch64-linux-gnu.so
genie/cli/commands/develop.cpython-312-aarch64-linux-gnu.so
genie/cli/commands/diff.cpython-312-aarch64-linux-gnu.so
genie/cli/commands/dnac.cpython-312-aarch64-linux-gnu.so
genie/cli/commands/git_repo_data.yaml
genie/cli/commands/job.py
genie/cli/commands/learn.cpython-312-aarch64-linux-gnu.so
genie/cli/commands/parser.cpython-312-aarch64-linux-gnu.so
genie/cli/commands/run.cpython-312-aarch64-linux-gnu.so
genie/cli/commands/shell.cpython-312-aarch64-linux-gnu.so
genie/cli/commands/undevelop.cpython-312-aarch64-linux-gnu.so
genie/conf/__init__.py
genie/conf/main.cpython-312-aarch64-linux-gnu.so
genie/conf/base/__init__.py
genie/conf/base/api.cpython-312-aarch64-linux-gnu.so
genie/conf/base/attributes.cpython-312-aarch64-linux-gnu.so
genie/conf/base/base.py
genie/conf/base/cli.cpython-312-aarch64-linux-gnu.so
genie/conf/base/config.cpython-312-aarch64-linux-gnu.so
genie/conf/base/decorator.cpython-312-aarch64-linux-gnu.so
genie-25.9.dist-info/METADATA
genie-25.9.dist-info/WHEEL
genie-25.9.dist-info/entry_points.txt
genie-25.9.dist-info/top_level.txt
genie-25.9.dist-info/RECORD
