Metadata-Version: 2.1
Name: genie
Version: 25.9
Summary: Genie: THE standard pyATS Library System
Home-page: https://developer.cisco.com/pyats/
Author: Cisco Systems Inc.
Author-email: pyats-support-ext@cisco.com
License: Apache 2.0
Keywords: genie pyats test automation cisco netdevops
Classifier: Development Status :: 6 - Mature
Classifier: Development Status :: 5 - Production/Stable
Classifier: Environment :: Console
Classifier: Intended Audience :: Developers
Classifier: Intended Audience :: Telecommunications Industry
Classifier: Intended Audience :: Information Technology
Classifier: Intended Audience :: System Administrators
Classifier: License :: OSI Approved :: Apache Software License
Classifier: Operating System :: MacOS
Classifier: Operating System :: POSIX :: Linux
Classifier: Programming Language :: Python :: 3.13
Classifier: Programming Language :: Python :: 3.12
Classifier: Programming Language :: Python :: 3.11
Classifier: Programming Language :: Python :: 3.10
Classifier: Programming Language :: Python :: 3.9
Classifier: Programming Language :: Python :: 3 :: Only
Classifier: Programming Language :: Python :: Implementation :: CPython
Classifier: Topic :: Software Development :: Testing
Classifier: Topic :: Software Development :: Build Tools
Classifier: Topic :: Software Development :: Libraries
Classifier: Topic :: Software Development :: Libraries :: Python Modules
Requires-Python: >=3.8
Requires-Dist: PrettyTable
Requires-Dist: tqdm
Requires-Dist: dill
Requires-Dist: jsonpickle
Requires-Dist: netaddr>=0.10.1
Requires-Dist: genie.libs.conf<25.10.0,>=25.9.0
Requires-Dist: genie.libs.clean<25.10.0,>=25.9.0
Requires-Dist: genie.libs.health<25.10.0,>=25.9.0
Requires-Dist: genie.libs.filetransferutils<25.10.0,>=25.9.0
Requires-Dist: genie.libs.ops<25.10.0,>=25.9.0
Requires-Dist: genie.libs.parser<25.10.0,>=25.9.0
Requires-Dist: genie.libs.sdk<25.10.0,>=25.9.0
Provides-Extra: dev
Requires-Dist: coverage; extra == "dev"
Requires-Dist: restview; extra == "dev"
Requires-Dist: Sphinx; extra == "dev"
Requires-Dist: sphinx-rtd-theme; extra == "dev"
Provides-Extra: full
Requires-Dist: genie.libs.conf; extra == "full"
Requires-Dist: genie.libs.clean; extra == "full"
Requires-Dist: genie.libs.health; extra == "full"
Requires-Dist: genie.libs.filetransferutils; extra == "full"
Requires-Dist: genie.libs.ops; extra == "full"
Requires-Dist: genie.libs.parser; extra == "full"
Requires-Dist: genie.libs.sdk; extra == "full"
Requires-Dist: pyats.robot<25.10.0,>=25.9.0; extra == "full"
Requires-Dist: genie.libs.robot<25.10.0,>=25.9.0; extra == "full"
Requires-Dist: genie.telemetry<25.10.0,>=25.9.0; extra == "full"
Requires-Dist: genie.trafficgen<25.10.0,>=25.9.0; extra == "full"
Provides-Extra: robot
Requires-Dist: pyats.robot<25.10.0,>=25.9.0; extra == "robot"
Requires-Dist: genie.libs.robot<25.10.0,>=25.9.0; extra == "robot"
